sleeper/__init__.py
sleeper/_version.py
sleeper/api/__init__.py
sleeper/api/_constants.py
sleeper/api/_types.py
sleeper/api/_utils.py
sleeper/api/avatar.py
sleeper/api/draft.py
sleeper/api/league.py
sleeper/api/player.py
sleeper/api/user.py
test/integration/__init__.py
test/integration/test_api/__init__.py
test/integration/test_api/constants.py
test/integration/test_api/test_avatar.py
test/integration/test_api/test_draft.py
test/integration/test_api/test_league.py
test/integration/test_api/test_player.py
test/integration/test_api/test_user.py
test/unit/__init__.py
test/unit/test_api/__init__.py
test/unit/test_api/test_avatar.py
test/unit/test_api/test_draft.py
test/unit/test_api/test_league.py
test/unit/test_api/test_player.py
test/unit/test_api/test_user.py
test/unit/test_api/test_utils.py
sleeper-2.0.0.dist-info/LICENSE
sleeper-2.0.0.dist-info/METADATA
sleeper-2.0.0.dist-info/WHEEL
sleeper-2.0.0.dist-info/top_level.txt
sleeper-2.0.0.dist-info/RECORD
