Metadata-Version: 2.1
Name: sleeper
Version: 2.0.0
Summary: A Python wrapper for the Sleeper API.
Home-page: https://github.com/joeyagreco/sleeper
Author: Joey Greco
Author-email: joeyagreco@gmail.com
License: MIT
Keywords: nfl football sleeper sleeper-api sleeper-fantasy-football fantasy-football wrapper wrapper-api
Requires-Python: >=3.10
License-File: LICENSE
Requires-Dist: requests~=2.32.3
